dotdiff/__init__.py
dotdiff/all_diffs.py
dotdiff/diff_generator.py
dotdiff-0.2.1.dist-info/licenses/LICENSE
dotdiff-0.2.1.dist-info/METADATA
dotdiff-0.2.1.dist-info/WHEEL
dotdiff-0.2.1.dist-info/entry_points.txt
dotdiff-0.2.1.dist-info/top_level.txt
dotdiff-0.2.1.dist-info/RECORD
