Metadata-Version: 2.4
Name: dotdiff
Version: 0.2.1
Summary: Generate semantic visual diffs for DOT graph files in Git repos
Author-email: Austin Song <austinjsong19@gmail.com>
License: MIT
Requires-Python: >=3.7
License-File: LICENSE
Requires-Dist: pydot
Requires-Dist: GitPython
Dynamic: license-file
